jenfi_pipeline_data_app/API.md
jenfi_pipeline_data_app/__init__.py
jenfi_pipeline_data_app/_pdoc.py
jenfi_pipeline_data_app/app.py
jenfi_pipeline_data_app/app_funcs/_constants.py
jenfi_pipeline_data_app/app_funcs/_db_handler.py
jenfi_pipeline_data_app/app_funcs/_exit_program.py
jenfi_pipeline_data_app/app_funcs/_models_s3.py
jenfi_pipeline_data_app/app_funcs/_parameters.py
jenfi_pipeline_data_app/app_funcs/_query.py
jenfi_pipeline_data_app/app_funcs/_result.py
jenfi_pipeline_data_app/app_funcs/_test_funcs.py
jenfi_pipeline_data_app/config/db.py
jenfi_pipeline_data_app/config/s3.py
jenfi_pipeline_data_app/db_cache/__init__.py
jenfi_pipeline_data_app/db_cache/cacher.py
jenfi_pipeline_data_app/db_cache/db_cache.py
jenfi_pipeline_data_app/db_models.py
jenfi_pipeline_data_app-0.5.5.dist-info/METADATA
jenfi_pipeline_data_app-0.5.5.dist-info/WHEEL
jenfi_pipeline_data_app-0.5.5.dist-info/entry_points.txt
jenfi_pipeline_data_app-0.5.5.dist-info/RECORD
