Metadata-Version: 2.1
Name: jenfi-pipeline-data-app
Version: 0.5.5
Summary: 
Author: Justin Louie
Author-email: 224840+nitsujri@users.noreply.github.com
Requires-Python: >=3.10,<3.11
Classifier: Programming Language :: Python :: 3
Classifier: Programming Language :: Python :: 3.10
Requires-Dist: SQLAlchemy (>=1.4.40,<2.0.0)
Requires-Dist: boto3 (>=1.24.78,<2.0.0)
Requires-Dist: catboost (>=1.2.3,<2.0.0)
Requires-Dist: jupyterlab-git (>=0.41.0,<0.42.0)
Requires-Dist: levenshtein (>=0.21.0,<0.22.0)
Requires-Dist: numpy (>=1.23.2,<2.0.0)
Requires-Dist: pandas (==2.2)
Requires-Dist: psycopg2 (>=2.9.3,<3.0.0)
Requires-Dist: python-dotenv (>=0.20.0,<0.21.0)
Requires-Dist: sagemaker (>=2.150.0,<3.0.0)
Requires-Dist: scikit-learn (>=1.1.2,<2.0.0)
Requires-Dist: sqlparse (>=0.4.2,<0.5.0)
Requires-Dist: statsmodels (>=0.13.5,<0.14.0)
